codequestion/__init__.py
codequestion/console.py
codequestion/download.py
codequestion/evaluate.py
codequestion/index.py
codequestion/models.py
codequestion/path.py
codequestion/search.py
codequestion/tokenizer.py
codequestion/topics.py
codequestion/vectors.py
codequestion/etl/__init__.py
codequestion/etl/stackexchange/__init__.py
codequestion/etl/stackexchange/db2qa.py
codequestion/etl/stackexchange/decompress.py
codequestion/etl/stackexchange/execute.py
codequestion/etl/stackexchange/sift.py
codequestion/etl/stackexchange/xml2db.py
codequestion-2.1.0.dist-info/LICENSE
codequestion-2.1.0.dist-info/METADATA
codequestion-2.1.0.dist-info/WHEEL
codequestion-2.1.0.dist-info/entry_points.txt
codequestion-2.1.0.dist-info/top_level.txt
codequestion-2.1.0.dist-info/RECORD
