Metadata-Version: 2.1
Name: codequestion
Version: 2.1.0
Summary: Ask coding questions directly from the terminal
Home-page: https://github.com/neuml/codequestion
Author: NeuML
License: Apache 2.0: http://www.apache.org/licenses/LICENSE-2.0
Project-URL: Documentation, https://github.com/neuml/codequestion
Project-URL: Issue Tracker, https://github.com/neuml/codequestion/issues
Project-URL: Source Code, https://github.com/neuml/codequestion
Keywords: search embedding machine-learning nlp
Classifier: License :: OSI Approved :: Apache Software License
Classifier: Operating System :: OS Independent
Classifier: Programming Language :: Python :: 3
Classifier: Topic :: Scientific/Engineering :: Artificial Intelligence
Classifier: Topic :: Software Development
Classifier: Topic :: Text Processing :: Indexing
Classifier: Topic :: Utilities
Requires-Python: >=3.8
License-File: LICENSE
Requires-Dist: html2markdown (>=0.1.7)
Requires-Dist: rich (>=12.0.1)
Requires-Dist: scipy (>=1.4.1)
Requires-Dist: tqdm (>=4.48.0)
Requires-Dist: txtai[graph] (>=6.0.0)
